servodoor_app/__init__.py
servodoor_app/main.py
servodoor_app/main.qml
servodoor_app-0.1.1.dist-info/LICENSE.txt
servodoor_app-0.1.1.dist-info/LICENSE.txt~
servodoor_app-0.1.1.dist-info/METADATA
servodoor_app-0.1.1.dist-info/WHEEL
servodoor_app-0.1.1.dist-info/entry_points.txt
servodoor_app-0.1.1.dist-info/RECORD
