Metadata-Version: 2.1
Name: servodoor-app
Version: 0.1.1
Summary: A simple GUI for controlling upto 18 (RC servo) t-maze doors.
Home-page: https://github.com/willdickson/servodoor-app
License: MIT
Author: Will Dickson
Author-email: wbd@caltech.edu
Requires-Python: >=3.10,<3.12
Classifier: Development Status :: 3 - Alpha
Classifier: Intended Audience :: Science/Research
Classifier: License :: OSI Approved :: MIT License
Classifier: Programming Language :: Python :: 3
Classifier: Programming Language :: Python :: 3.10
Classifier: Programming Language :: Python :: 3.11
Requires-Dist: adafruit-ampy (>=1.1.0,<2.0.0)
Requires-Dist: pyserial (>=3.5,<4.0)
Requires-Dist: pyside6 (>=6.5.2,<7.0.0)
Requires-Dist: servodoor (>=0.1,<0.2)
Project-URL: Repository, https://github.com/willdickson/servodoor-app
